RPi-stubs/METADATA.toml
RPi-stubs/__init__.pyi
RPi-stubs/py.typed
RPi-stubs/GPIO/__init__.pyi
types_rpi_gpio-0.7.0.20250318.dist-info/LICENSE
types_rpi_gpio-0.7.0.20250318.dist-info/METADATA
types_rpi_gpio-0.7.0.20250318.dist-info/WHEEL
types_rpi_gpio-0.7.0.20250318.dist-info/top_level.txt
types_rpi_gpio-0.7.0.20250318.dist-info/RECORD
